azext_managementpartner/__init__.py
azext_managementpartner/_client_factory.py
azext_managementpartner/_exception_handler.py
azext_managementpartner/_help.py
azext_managementpartner/_params.py
azext_managementpartner/commands.py
azext_managementpartner/custom.py
azext_managementpartner/managementpartner/__init__.py
azext_managementpartner/managementpartner/ace_provisioning_management_partner_api.py
azext_managementpartner/managementpartner/version.py
azext_managementpartner/managementpartner/models/__init__.py
azext_managementpartner/managementpartner/models/error.py
azext_managementpartner/managementpartner/models/extended_error_info.py
azext_managementpartner/managementpartner/models/operation_display.py
azext_managementpartner/managementpartner/models/operation_response.py
azext_managementpartner/managementpartner/models/operation_response_paged.py
azext_managementpartner/managementpartner/models/partner_response.py
azext_managementpartner/managementpartner/operations/__init__.py
azext_managementpartner/managementpartner/operations/operation_operations.py
azext_managementpartner/managementpartner/operations/partner_operations.py
managementpartner-0.1.2.dist-info/DESCRIPTION.rst
managementpartner-0.1.2.dist-info/METADATA
managementpartner-0.1.2.dist-info/RECORD
managementpartner-0.1.2.dist-info/WHEEL
managementpartner-0.1.2.dist-info/metadata.json
managementpartner-0.1.2.dist-info/top_level.txt
